[{"N":10,"mu":0.0,"back_mu":0,"fp_ALLD":0.8731,"fp_ALLC_given_ALLD_extinct":1.0,"fraction_ALLC_when_ALLD_extinct":1.0},{"N":10,"mu":0.0526315789,"back_mu":0,"fp_ALLD":0.6918,"fp_ALLC_given_ALLD_extinct":0.7112264763,"fraction_ALLC_when_ALLD_extinct":0.569467878},{"N":10,"mu":0.1052631579,"back_mu":0,"fp_ALLD":0.5622,"fp_ALLC_given_ALLD_extinct":0.6521242577,"fraction_ALLC_when_ALLD_extinct":0.4668341709},{"N":10,"mu":0.1578947368,"back_mu":0,"fp_ALLD":0.4575,"fp_ALLC_given_ALLD_extinct":0.6368663594,"fraction_ALLC_when_ALLD_extinct":0.4196682028},{"N":10,"mu":0.2105263158,"back_mu":0,"fp_ALLD":0.3753,"fp_ALLC_given_ALLD_extinct":0.6321434288,"fraction_ALLC_when_ALLD_extinct":0.3912598047},{"N":10,"mu":0.2631578947,"back_mu":0,"fp_ALLD":0.3086,"fp_ALLC_given_ALLD_extinct":0.6167196992,"fraction_ALLC_when_ALLD_extinct":0.3653022852},{"N":10,"mu":0.3157894737,"back_mu":0,"fp_ALLD":0.2603,"fp_ALLC_given_ALLD_extinct":0.6141679059,"fraction_ALLC_when_ALLD_extinct":0.3524536974},{"N":10,"mu":0.3684210526,"back_mu":0,"fp_ALLD":0.2157,"fp_ALLC_given_ALLD_extinct":0.6033405585,"fraction_ALLC_when_ALLD_extinct":0.3311232947},{"N":10,"mu":0.4210526316,"back_mu":0,"fp_ALLD":0.1856,"fp_ALLC_given_ALLD_extinct":0.5820235756,"fraction_ALLC_when_ALLD_extinct":0.3051694499},{"N":10,"mu":0.4736842105,"back_mu":0,"fp_ALLD":0.1633,"fp_ALLC_given_ALLD_extinct":0.5770288036,"fraction_ALLC_when_ALLD_extinct":0.292912633},{"N":10,"mu":0.5263157895,"back_mu":0,"fp_ALLD":0.1396,"fp_ALLC_given_ALLD_extinct":0.5625290563,"fraction_ALLC_when_ALLD_extinct":0.2808344956},{"N":10,"mu":0.5789473684,"back_mu":0,"fp_ALLD":0.125,"fp_ALLC_given_ALLD_extinct":0.5421714286,"fraction_ALLC_when_ALLD_extinct":0.26232},{"N":10,"mu":0.6315789474,"back_mu":0,"fp_ALLD":0.1032,"fp_ALLC_given_ALLD_extinct":0.5314451383,"fraction_ALLC_when_ALLD_extinct":0.2512377342},{"N":10,"mu":0.6842105263,"back_mu":0,"fp_ALLD":0.0947,"fp_ALLC_given_ALLD_extinct":0.5069037888,"fraction_ALLC_when_ALLD_extinct":0.2348282337},{"N":10,"mu":0.7368421053,"back_mu":0,"fp_ALLD":0.0867,"fp_ALLC_given_ALLD_extinct":0.4835212964,"fraction_ALLC_when_ALLD_extinct":0.2210883609},{"N":10,"mu":0.7894736842,"back_mu":0,"fp_ALLD":0.0699,"fp_ALLC_given_ALLD_extinct":0.4447908827,"fraction_ALLC_when_ALLD_extinct":0.1965165036},{"N":10,"mu":0.8421052632,"back_mu":0,"fp_ALLD":0.0657,"fp_ALLC_given_ALLD_extinct":0.4426843626,"fraction_ALLC_when_ALLD_extinct":0.1965535695},{"N":10,"mu":0.8947368421,"back_mu":0,"fp_ALLD":0.0602,"fp_ALLC_given_ALLD_extinct":0.4106192807,"fraction_ALLC_when_ALLD_extinct":0.1795488402},{"N":10,"mu":0.9473684211,"back_mu":0,"fp_ALLD":0.0529,"fp_ALLC_given_ALLD_extinct":0.3823249921,"fraction_ALLC_when_ALLD_extinct":0.1687255834},{"N":10,"mu":1.0,"back_mu":0,"fp_ALLD":0.0551,"fp_ALLC_given_ALLD_extinct":0.3624722193,"fraction_ALLC_when_ALLD_extinct":0.1632236215}]